Metadata-Version: 2.1
Name: tableqa
Version: 0.0.10
Summary: Tool for querying natural language on tabular data
Home-page: https://github.com/abhijithneilabraham/tableQA
Author: Abhijith Neil Abraham, Fariz Rahman
Author-email: abhijithneilabrahampk@gmail.com,farizrahman4u@gmail.com
License: GNU GPL v2
Platform: UNKNOWN
Requires-Python: >=3.6
Requires-Dist: responder
Requires-Dist: graphql-core (==2.3)
Requires-Dist: graphene (==2.1.8)
Requires-Dist: transformers[tf-cpu] (==3.0.2)
Requires-Dist: rake-nltk
Requires-Dist: nltk
Requires-Dist: sqlalchemy
Requires-Dist: tensorflow-hub
Requires-Dist: pandas
Requires-Dist: matplotlib
